cadet/__init__.py
cadet/cadet.py
cadet/cadet_dll.py
cadet/cadet_dll_parameterprovider.py
cadet/cadet_dll_utils.py
cadet/h5.py
cadet/runner.py
cadet_python-1.1.2.dist-info/licenses/LICENSE
cadet_python-1.1.2.dist-info/METADATA
cadet_python-1.1.2.dist-info/WHEEL
cadet_python-1.1.2.dist-info/top_level.txt
cadet_python-1.1.2.dist-info/RECORD
