Metadata-Version: 2.4
Name: CADET-Python
Version: 1.1.2
Summary: CADET-Python is a Python interface to the CADET-Core simulator
Author-email: William Heymann <w.heymann@fz-juelich.de>, Samuel Leweke <s.leweke@fz-juelich.de>, Johannes Schmölder <j.schmoelder@fz-juelich.de>, Ronald Jäpel <r.jaepel@fz-juelich.de>
License: BSD-3-Clause
Project-URL: homepage, https://github.com/cadet/CADET-Python
Project-URL: Bug Tracker, https://github.com/cadet/CADET-Python/issues
Keywords: process modeling,process optimization,chromatography
Classifier: Programming Language :: Python :: 3
Classifier: Operating System :: OS Independent
Classifier: License :: OSI Approved :: BSD License
Classifier: Intended Audience :: Science/Research
Requires-Python: >=3.10
License-File: LICENSE
Requires-Dist: addict
Requires-Dist: numpy
Requires-Dist: h5py
Requires-Dist: filelock
Provides-Extra: testing
Requires-Dist: pytest; extra == "testing"
Requires-Dist: joblib; extra == "testing"
Dynamic: license-file
